LICENSE
README.md
pyproject.toml
setup.py
./midivision/__init__.py
midivision/__init__.py
midivision.egg-info/PKG-INFO
midivision.egg-info/SOURCES.txt
midivision.egg-info/dependency_links.txt
midivision.egg-info/entry_points.txt
midivision.egg-info/requires.txt
midivision.egg-info/top_level.txt