Metadata-Version: 2.1
Name: midivision
Version: 0.1
Summary: Division
Home-page: https://pypi.org/project/midivision
Author: Diego Alejandro Acosta
Author-email: diego.acostab@udea.edu.co
License: MIT
Keywords: math
Classifier: Programming Language :: Python :: 3
Classifier: License :: OSI Approved :: MIT License
Classifier: Operating System :: OS Independent
License-File: LICENSE
